mcnews/__init__.py
mcnews/searchapi.py
mcnews/util.py
mediacloud_news_client-2.0.0.dist-info/LICENSE
mediacloud_news_client-2.0.0.dist-info/METADATA
mediacloud_news_client-2.0.0.dist-info/WHEEL
mediacloud_news_client-2.0.0.dist-info/top_level.txt
mediacloud_news_client-2.0.0.dist-info/RECORD
