Metadata-Version: 2.1
Name: mediacloud-news-client
Version: 2.0.0
Summary: Mediacloud news archive search api client
Maintainer: Rahul Bhargava
Maintainer-email: r.bhargava@northeastern.edu
Project-URL: Bug Reports, https://github.com/mediacloud/mediacloud-news-client/issues
Project-URL: Source, https://github.com/mediacloud/mediacloud-news-client
Requires-Python: >3.7
License-File: LICENSE
Requires-Dist: requests ==2.*
Requires-Dist: ciso8601 ==2.2.*
Provides-Extra: dev
Requires-Dist: pytest ; extra == 'dev'
Requires-Dist: twine ; extra == 'dev'
